kyototycoon/__init__.py
kyototycoon/kt_binary.py
kyototycoon/kt_common.py
kyototycoon/kt_error.py
kyototycoon/kt_http.py
kyototycoon/kyotoslave.py
kyototycoon/kyototycoon.py
kyototycoon/packers.py
python_kyototycoon_ng-0.7.5.dist-info/COPYING
python_kyototycoon_ng-0.7.5.dist-info/METADATA
python_kyototycoon_ng-0.7.5.dist-info/WHEEL
python_kyototycoon_ng-0.7.5.dist-info/top_level.txt
python_kyototycoon_ng-0.7.5.dist-info/RECORD
