Metadata-Version: 2.1
Name: python-kyototycoon-ng
Version: 0.7.5
Summary: Python client for Kyoto Tycoon key-value store
Home-page: https://github.com/carlosefr/python-kyototycoon-ng
Author: Toru Maesaka
Author-email: dev@torum.net
Maintainer: Carlos Rodrigues
Maintainer-email: cefrodrigues@gmail.com
License: BSD
Keywords: Kyoto Tycoon,Kyoto Cabinet
Platform: UNKNOWN
Classifier: Development Status :: 5 - Production/Stable
Classifier: Environment :: Console
Classifier: License :: OSI Approved :: BSD License
Classifier: Programming Language :: Python :: 2
Classifier: Programming Language :: Python :: 3
Classifier: Topic :: Software Development :: Libraries
Classifier: Intended Audience :: Developers
